[
  {
    "key": 1,
    "title": "Азербайджанская музыка",
    "desc": "Азербайджанская музыка отличается богатой многовековой историей и традициями. Музыка Азербайджана обогатила сокровищницу мировой музыкальной культуры яркими примерами истинного таланта и свободного творчества простых жителей страны. Почетное место в музыкальном творчестве Азербайджана занимают мугамы – вокально-инструментальные произведения, которые в классическом варианте исполняются одним вокалистом и двумя музыкантами.",
    "image": "/musicMain.jpeg",
    "musicians": [
      {
        "key": 1,
        "name": "Рашид Бехбутов",
        "text": "Советский азербайджанский эстрадный и оперный певец (лирический тенор) и актёр",
        "image": "/rashid.jpeg",
        "audio": "/rashid_audio.mp3"

      },
      {
        "key": 2,
        "name": "Узеир Гаджибеков",
        "text": "Советский азербайджанский эстрадный и оперный певец (лирический тенор) и актёр",
        "image": "/uzeir.jpeg",
        "audio": "/uzeir_audio.mp3"

      },
      {
        "key": 3,
        "name": "Шавкет Алекберова",
        "text": "Советский азербайджанский эстрадный и оперный певец (лирический тенор) и актёр",
        "image": "/shovkat.jpeg",
        "audio": "/sovket_audio.mp3"

      }, 
      {
        "key": 4,
        "name": "Муслим Магомаев",
        "text": "Советский, азербайджанский и российский эстрадный и оперный певец и композитор.",
        "image": "/muslim.jpg",
        "audio": "/muslim_audio.mp3"

      },

      {
        "key": 5,
        "name": "Зейнеб Ханларова",
        "text": "Советский азербайджанский эстрадный и оперный певец (лирический тенор) и актёр",
        "image": "/zeyneb.jpg",
        "audio": "/zeyneb_auido.mp3"

      },

      {
        "key": 6,
        "name": "Полад Бюль-Бюль",
        "text": "Советский и азербайджанский эстрадный певец, композитор, педагог, дипломат.",
        "image": "/polad.jpg",
        "audio": "/polad_audio.mp3"

      }
    ]
  }
]
